zapr_mcp/__init__.py
zapr_mcp/__main__.py
zapr_mcp/server.py
zapr_mcp-1.0.1.dist-info/licenses/LICENSE
zapr_mcp-1.0.1.dist-info/METADATA
zapr_mcp-1.0.1.dist-info/WHEEL
zapr_mcp-1.0.1.dist-info/entry_points.txt
zapr_mcp-1.0.1.dist-info/top_level.txt
zapr_mcp-1.0.1.dist-info/RECORD
