Metadata-Version: 2.4
Name: zapr-mcp
Version: 1.0.1
Summary: Zapr WhatsApp MCP Client for Model Context Protocol
Author-email: Zapr <contact@zapr.link>
License-Expression: MIT
Project-URL: Homepage, https://zapr.link
Project-URL: Repository, https://github.com/zapr-link/zapr-mcp
Project-URL: Documentation, https://docs.zapr.link
Keywords: mcp,whatsapp,model-context-protocol,ai,messaging
Classifier: Development Status :: 4 - Beta
Classifier: Intended Audience :: Developers
Classifier: Programming Language :: Python :: 3
Classifier: Programming Language :: Python :: 3.8
Classifier: Programming Language :: Python :: 3.9
Classifier: Programming Language :: Python :: 3.10
Classifier: Programming Language :: Python :: 3.11
Classifier: Programming Language :: Python :: 3.12
Requires-Python: >=3.10
License-File: LICENSE
Requires-Dist: mcp>=1.0.0
Requires-Dist: aiohttp>=3.8.0
Dynamic: license-file
